{
  "id": "kr-OGSUsOoOhpI",
  "title": "날 봐 귀순",
  "artist": "대성",
  "youtubeId": "OGSUsOoOhpI",
  "mood": "",
  "cards": [
    {
      "text": "오늘 하루도\n활짝 웃으며\n힘차게 시작하세요",
      "emoji": "😄",
      "gradient": "sunrise",
      "category": "인사"
    },
    {
      "text": "당신이 계셔서\n제 삶이\n노래가 됩니다",
      "emoji": "🎵",
      "gradient": "warm",
      "category": "감사"
    },
    {
      "text": "흥이 나는 날엔\n어깨춤 한 번\n추어 보세요",
      "emoji": "💃",
      "gradient": "rose",
      "category": "축복"
    },
    {
      "text": "보고 싶은 마음\n한가득 담아\n안부를 전합니다",
      "emoji": "💌",
      "gradient": "lavender",
      "category": "인사"
    },
    {
      "text": "웃음이 많은 사람 곁엔\n좋은 일도\n따라옵니다",
      "emoji": "🌈",
      "gradient": "spring",
      "category": "명언"
    },
    {
      "text": "멀리 있어도\n마음은 늘\n곁에 있습니다",
      "emoji": "🤍",
      "gradient": "calm",
      "category": "위로"
    },
    {
      "text": "건강한 하루가\n제일 큰\n복입니다",
      "emoji": "🍀",
      "gradient": "spring",
      "category": "건강"
    },
    {
      "text": "오늘도 당신께\n좋은 일만\n가득하길",
      "emoji": "🌷",
      "gradient": "warm",
      "category": "축복"
    },
    {
      "text": "신나는 노래처럼\n가벼운 마음으로\n하루를 사세요",
      "emoji": "🎶",
      "gradient": "sunrise",
      "category": "명언"
    },
    {
      "text": "밥 잘 챙겨 드시고\n따뜻하게\n지내세요",
      "emoji": "🍚",
      "gradient": "warm",
      "category": "건강"
    },
    {
      "text": "당신 웃는 얼굴이\n제겐 제일\n예쁜 꽃입니다",
      "emoji": "🌸",
      "gradient": "rose",
      "category": "감사"
    },
    {
      "text": "흥겨운 가락 따라\n근심일랑\n훌훌 털어요",
      "emoji": "🥁",
      "gradient": "sunset",
      "category": "위로"
    },
    {
      "text": "보고 싶어 부르는\n그 이름 하나에\n마음이 환해집니다",
      "emoji": "💖",
      "gradient": "rose",
      "category": "인사"
    },
    {
      "text": "오늘 밤엔\n편안한 잠\n푹 주무세요",
      "emoji": "🌙",
      "gradient": "night",
      "category": "인사"
    },
    {
      "text": "즐거운 마음이\n제일 좋은\n약입니다",
      "emoji": "😊",
      "gradient": "spring",
      "category": "건강"
    },
    {
      "text": "함께한 시간들이\n제겐 모두\n선물이었어요",
      "emoji": "🎁",
      "gradient": "lavender",
      "category": "감사"
    },
    {
      "text": "어깨 펴고\n환하게 웃는\n하루 보내세요",
      "emoji": "☀️",
      "gradient": "sunrise",
      "category": "축복"
    },
    {
      "text": "살다 보면\n좋은 날이\n꼭 찾아옵니다",
      "emoji": "🌤️",
      "gradient": "calm",
      "category": "위로"
    },
    {
      "text": "바람 좋은 계절에\n가벼운 걸음으로\n나들이 어떠세요",
      "emoji": "🍃",
      "gradient": "spring",
      "category": "계절"
    },
    {
      "text": "늘 그 자리에서\n건강하게\n행복하세요",
      "emoji": "🌻",
      "gradient": "warm",
      "category": "축복"
    }
  ]
}
